README.md
setup.py
number_to_string/__init__.py
number_to_string/core.py
number_to_string.egg-info/PKG-INFO
number_to_string.egg-info/SOURCES.txt
number_to_string.egg-info/dependency_links.txt
number_to_string.egg-info/top_level.txt
number_to_string/tests/__init__.py
number_to_string/tests/test_helper.py