Metadata-Version: 1.0
Name: number-to-string
Version: 1.0.3
Summary: UNKNOWN
Home-page: https://github.com/berenda-andrey/ru_number_to_text
Author: Andrey Berenda
Author-email: berenda.andrey@gmail.com
License: MIT
Platform: UNKNOWN
